ligonlibrary/__init__.py
ligonlibrary/authinfo.py
ligonlibrary/dataframes.py
ligonlibrary/email_from_ligon.py
ligonlibrary/strings.py
ligonlibrary-0.1.6.dist-info/METADATA
ligonlibrary-0.1.6.dist-info/WHEEL
ligonlibrary-0.1.6.dist-info/RECORD
