Metadata-Version: 2.3
Name: ligonlibrary
Version: 0.1.6
Summary: Various little hacks.
License: CC-BY-4.0
Author: Ethan Ligon
Author-email: ligon@berkeley.edu
Requires-Python: >=3.11
Classifier: License :: Other/Proprietary License
Classifier: Programming Language :: Python :: 3
Classifier: Programming Language :: Python :: 3.11
Classifier: Programming Language :: Python :: 3.12
Classifier: Programming Language :: Python :: 3.13
Requires-Dist: google-api-python-client (>=2.178.0,<3.0.0)
Requires-Dist: google-auth-oauthlib (>=1.2.2,<2.0.0)
Requires-Dist: pandas (>=2.3.1,<3.0.0)
Requires-Dist: thefuzz (>=0.22.1,<0.23.0)
